libvgazer/__init__.py
libvgazer/checkers_manager.py
libvgazer/command.py
libvgazer/env_vars.py
libvgazer/exceptions.py
libvgazer/host_detector.py
libvgazer/installers_manager.py
libvgazer/licenses.py
libvgazer/os_release.py
libvgazer/platform.py
libvgazer/utils.py
libvgazer/working_dir.py
libvgazer/config/__init__.py
libvgazer/config/cmake.py
libvgazer/config/meson.py
libvgazer/install/__init__.py
libvgazer/install/apt.py
libvgazer/install/cmd.py
libvgazer/install/custom.py
libvgazer/install/dnf.py
libvgazer/install/pacman.py
libvgazer/install/pip3.py
libvgazer/install/yum.py
libvgazer/install/custom_installer/__init__.py
libvgazer/install/custom_installer/alsa-lib.py
libvgazer/install/custom_installer/autoconf.py
libvgazer/install/custom_installer/automake.py
libvgazer/install/custom_installer/cfgpath.py
libvgazer/install/custom_installer/cjson.py
libvgazer/install/custom_installer/cmake.py
libvgazer/install/custom_installer/cmake_barebones.py
libvgazer/install/custom_installer/cmocka.py
libvgazer/install/custom_installer/codecoverage.py
libvgazer/install/custom_installer/cwalk.py
libvgazer/install/custom_installer/dr_wav.py
libvgazer/install/custom_installer/expat.py
libvgazer/install/custom_installer/hash_table.py
libvgazer/install/custom_installer/icu.py
libvgazer/install/custom_installer/icu_54_2.py
libvgazer/install/custom_installer/inih.py
libvgazer/install/custom_installer/iwyu.py
libvgazer/install/custom_installer/ketopt.py
libvgazer/install/custom_installer/libclipboard.py
libvgazer/install/custom_installer/libffi.py
libvgazer/install/custom_installer/libglvnd.py
libvgazer/install/custom_installer/liblzma.py
libvgazer/install/custom_installer/libogg.py
libvgazer/install/custom_installer/libpng.py
libvgazer/install/custom_installer/libsir.py
libvgazer/install/custom_installer/libtool.py
libvgazer/install/custom_installer/libvorbis.py
libvgazer/install/custom_installer/libxext.py
libvgazer/install/custom_installer/luajit.py
vgazer-81.dist-info/COPYING
vgazer-81.dist-info/METADATA
vgazer-81.dist-info/WHEEL
vgazer-81.dist-info/top_level.txt
vgazer-81.dist-info/RECORD
