Metadata-Version: 2.1
Name: vgazer
Version: 81
Summary: Library for checking versions and installing various software
Home-page: https://github.com/Survival-SDK/vgazer
Author: Vasiliy Edomin
Author-email: vasiliy.edomin@gmail.com
License: CC0
Classifier: Development Status :: 2 - Pre-Alpha
Classifier: License :: CC0 1.0 Universal (CC0 1.0) Public Domain Dedication
Classifier: Natural Language :: English
Classifier: Operating System :: POSIX :: Linux
Classifier: Programming Language :: Python :: 3
Classifier: Topic :: Software Development :: Build Tools
License-File: COPYING
Requires-Dist: bs4
Requires-Dist: multimethod
Requires-Dist: requests
